vaxa_plotly_branding/__init__.py
vaxa_plotly_branding/vaxa_analytics_plot_logo.png
vaxa_plotly_branding/vaxa_plotly_template.py
vaxa_plotly_branding-3.2.0.dist-info/METADATA
vaxa_plotly_branding-3.2.0.dist-info/WHEEL
vaxa_plotly_branding-3.2.0.dist-info/RECORD
