Metadata-Version: 2.3
Name: vaxa-plotly-branding
Version: 3.2.0
Summary: 
Author: Curtis West
Author-email: curtis@curtiswest.net
Requires-Python: >=3.8
Classifier: Programming Language :: Python :: 3
Classifier: Programming Language :: Python :: 3.8
Classifier: Programming Language :: Python :: 3.9
Classifier: Programming Language :: Python :: 3.10
Classifier: Programming Language :: Python :: 3.11
Classifier: Programming Language :: Python :: 3.12
Classifier: Programming Language :: Python :: 3.13
Requires-Dist: pandas (>=1.5)
Requires-Dist: pillow (>=10.0)
Requires-Dist: plotly (>=5.0)
